turkishnlp/__init__.py
turkishnlp/detector.py
turkishnlp-0.0.5.dist-info/METADATA
turkishnlp-0.0.5.dist-info/RECORD
turkishnlp-0.0.5.dist-info/WHEEL
turkishnlp-0.0.5.dist-info/top_level.txt
