Metadata-Version: 2.1
Name: turkishnlp
Version: 0.0.5
Summary: A python script that processes Turkish language
Home-page: https://github.com/MeteHanC/turkishnlp
Author: Metehan Cetinkaya
Author-email: metehancet@gmail.com
Maintainer: Metehan Cetinkaya
Maintainer-email: metehancet@gmail.com
License: UNKNOWN
Keywords: turkishnlp,python,nlp,language processing
Platform: UNKNOWN
Classifier: Programming Language :: Python
Classifier: Environment :: MacOS X
Classifier: Programming Language :: Python :: 3
Classifier: Programming Language :: Python :: 3.6
